{"reminders":[{"name":"task default","nameFull":null,"time":"\/Date(1640514900000)\/","mindmap":"calander","mindmapPath":"D:\\Demo\\calander.mm","editCount":0,"isCompleted":false,"isCurrect":true,"isNew":false,"comleteTime":null,"editTime":null,"remindertype":"","rhours":0,"rdays":0,"rWeek":0,"rweeks":[],"rMonth":0,"ryear":0,"tasktime":0,"tasklevel":0,"ID":"ID_681177332","ebstring":0,"isview":false,"isEBType":false},{"name":"你好吗","nameFull":null,"time":"\/Date(1640813316870)\/","mindmap":"calander","mindmapPath":"D:\\Demo\\calander.mm","editCount":0,"isCompleted":false,"isCurrect":true,"isNew":false,"comleteTime":null,"editTime":null,"remindertype":"","rhours":0,"rdays":0,"rWeek":0,"rweeks":[],"rMonth":0,"ryear":0,"tasktime":300,"tasklevel":1,"ID":"988ade3f-c03d-43f1-a52e-8dccc0c67837","ebstring":0,"isview":false,"isEBType":false},{"name":"今天，很开心","nameFull":null,"time":"\/Date(1640631600000)\/","mindmap":"calander","mindmapPath":"D:\\Demo\\calander.mm","editCount":1,"isCompleted":false,"isCurrect":true,"isNew":false,"comleteTime":null,"editTime":["\/Date(1640807410563)\/"],"remindertype":"","rhours":0,"rdays":0,"rWeek":0,"rweeks":[],"rMonth":0,"ryear":0,"tasktime":210,"tasklevel":1,"ID":"6f5e75b2-91bc-4785-b082-7782f87ccb5a","ebstring":0,"isview":false,"isEBType":false},{"name":"很开心","nameFull":null,"time":"\/Date(1640743200000)\/","mindmap":"calander","mindmapPath":"D:\\Demo\\calander.mm","editCount":2,"isCompleted":false,"isCurrect":true,"isNew":false,"comleteTime":null,"editTime":["\/Date(1640732553331)\/","\/Date(1640807290958)\/"],"remindertype":"","rhours":0,"rdays":0,"rWeek":0,"rweeks":[],"rMonth":0,"ryear":0,"tasktime":180,"tasklevel":1,"ID":"12b3e461-7907-4b4d-b499-171419e7e444","ebstring":0,"isview":false,"isEBType":false},{"name":"你知道吗\r\n","nameFull":null,"time":"\/Date(1640903400000)\/","mindmap":"calander","mindmapPath":"D:\\Demo\\calander.mm","editCount":1,"isCompleted":false,"isCurrect":true,"isNew":false,"comleteTime":null,"editTime":["\/Date(1640732553331)\/"],"remindertype":"","rhours":0,"rdays":0,"rWeek":0,"rweeks":[],"rMonth":0,"ryear":0,"tasktime":30,"tasklevel":1,"ID":"50c313cd-d690-466b-9f67-a0d6165b9372","ebstring":0,"isview":false,"isEBType":false},{"name":"哈哈哈\r\n","nameFull":null,"time":"\/Date(1640836800000)\/","mindmap":"calander","mindmapPath":"D:\\Demo\\calander.mm","editCount":2,"isCompleted":false,"isCurrect":true,"isNew":false,"comleteTime":null,"editTime":["\/Date(1640807290958)\/","\/Date(1640807410563)\/"],"remindertype":"","rhours":0,"rdays":0,"rWeek":0,"rweeks":[],"rMonth":0,"ryear":0,"tasktime":30,"tasklevel":1,"ID":"cd0bba0c-82c9-436a-b390-bb7688566e77","ebstring":0,"isview":false,"isEBType":false}],"Fenleis":[],"editCount":6,"reminderCount":7,"NoFenleiMindmaps":["calander"],"mindmaps":""}